internal_match_hooks/__init__.py
internal_match_hooks/modifies_person_match_hooks.py
internal_match_hooks/resources/variables/vocab_refs.json
internal_match_hooks/util.py
internal_match_hooks-0.1.0.dist-info/WHEEL
internal_match_hooks-0.1.0.dist-info/METADATA
internal_match_hooks-0.1.0.dist-info/RECORD
